Workbook

Sheet Feuil1
A1: Date | B1: Comptes | C1: Montant
A2: 45657 | B2: 4500 | C2: 800000
A3: 45657 | B3: 5010 | C3: 100000
A4: 45657 | B4: 5100 | C4: 600000
A5: 45657 | B5: 5150 | C5: 60000
A6: 45657 | B6: 5300 | C6: 50150
A7: 45657 | B7: 5305 | C7: 30000
A8: 45657 | B8: 5420 | C8: 12000
A9: 45657 | B9: 5740 | C9: 7350
A10: 45657 | B10: 5725 | C10: 700
A11: 45657 | B11: 5726 | C11: 100
A12: 45657 | B12: 5650 | C12: 500
A13: 45657 | B13: 5345 | C13: 4000
... A18: 45657 | B18: 3300 | C18: 40000

Sheet Feuil2
A1: Date | B1: Comptes | C1: Montant
A2: 45657 | B2: 4120 | C2: 29000
A3: 45657 | B3: 5300 | C3: 8664
A4: 45657 | B4: 5420 | C4: 2000
A5: 45657 | B5: 5740 | C5: 818
A6: 45657 | B6: 5500 | C6: 2272
A7: 45657 | B7: 5640 | C7: 1636
A8: 45657 | B8: 3100 | C8: 60000
A9: 45657 | B9: 3200 | C9: 5000
A10: 45657 | B10: 3300 | C10: 3000
A11: 45657 | B11: 1010 | C11: 2000
A12: 45657 | B12: 1190 | C12: 3250
A13: 45657 | B13: 1400 | C13: 32860
... A18: 45657 | B18: 2900 | C18: 340000

Sheet Feuil3
A1: Date | B1: Comptes | C1: Montant
A2: 45383 | B2: 3200 | C2: 23857.95
A3: 45383 | B3: 1010 | C3: 23857.95
A4: 45383 | B4: 3200 | C4: 59273.46
A5: 45383 | B5: 1050 | C5: 59273.46
A6: 45383 | B6: 3200 | C6: 5199.89
A7: 45383 | B7: 1100 | C7: 5199.89
A8: 45383 | B8: 4160 | C8: 2120.71
A9: 45383 | B9: 1010 | C9: 2120.71
A10: 45384 | B10: 4160 | C10: 212
A11: 45384 | B11: 1010 | C11: 212
A12: 45390 | B12: 4160 | C12: 212
A13: 45390 | B13: 1010 | C13: 212
... A199: 45600 | B199: 1010 | C199: 212

Sheet Budget
A1: Date | B1: Comptes | C1: Montant
A2: 45383 | B2: 3200 | C2: 23857.95
A3: 45383 | B3: 1010 | C3: 23857.95
A4: 45383 | B4: 3200 | C4: 59273.46
A5: 45383 | B5: 1050 | C5: 59273.46
A6: 45383 | B6: 3200 | C6: 5199.89
A7: 45383 | B7: 1100 | C7: 5199.89
A8: 45383 | B8: 4160 | C8: 2120.71
A9: 45383 | B9: 1010 | C9: 2120.71
A10: 45383 | B10: 4160 | C10: 212
A11: 45383 | B11: 1010 | C11: 212
A12: 45383 | B12: 4160 | C12: 212
A13: 45383 | B13: 1010 | C13: 212
... A187: 45418 | B187: 5660 | C187: 1200

Sheet Feuil5
A1: Date | B1: Comptes | C1: Montant | D1: Description | E1: Explication
A2: 45658 | B2: 3200 | C2: 6201.05 | D2: =VLOOKUP(B2,'Plan Comptable'!A:B,2,FALSE) -> Apport
A3: 45658 | B3: 1010 | C3: 6201.05 | D3: =VLOOKUP(B3,'Plan Comptable'!A:B,2,FALSE) -> 0033830-EOP Épargne avec opérations (C)
A4: 45658 | B4: 3200 | C4: 6.15 | D4: =VLOOKUP(B4,'Plan Comptable'!A:B,2,FALSE) -> Apport
A5: 45658 | B5: 1100 | C5: 6.15 | D5: =VLOOKUP(B5,'Plan Comptable'!A:B,2,FALSE) -> 0033830-ET1 Compte avantage entreprise
A6: 45658 | B6: 3200 | C6: 95502.85 | D6: =VLOOKUP(B6,'Plan Comptable'!A:B,2,FALSE) -> Apport
A7: 45658 | B7: 1010 | C7: 95502.85 | D7: =VLOOKUP(B7,'Plan Comptable'!A:B,2,FALSE) -> 0033830-EOP Épargne avec opérations (C)
A8: 45663 | B8: 4160 | C8: 2332.73 | D8: =VLOOKUP(B8,'Plan Comptable'!A:B,2,FALSE) -> Cotisation
A9: 45663 | B9: 1010 | C9: 2332.73 | D9: =VLOOKUP(B9,'Plan Comptable'!A:B,2,FALSE) -> 0033830-EOP Épargne avec opérations (C)
A10: 45664 | B10: 4160 | C10: -212.11 | D10: =VLOOKUP(B10,'Plan Comptable'!A:B,2,FALSE) -> Cotisation | E10: Rebond Olivier
A11: 45664 | B11: 1010 | C11: -212.11 | D11: =VLOOKUP(B11,'Plan Comptable'!A:B,2,FALSE) -> 0033830-EOP Épargne avec opérations (C) | E11: Rebond Olivier
A12: 45670 | B12: 1010 | C12: -12.08 | D12: =VLOOKUP(B12,'Plan Comptable'!A:B,2,FALSE) -> 0033830-EOP Épargne avec opérations (C)
A13: 45670 | B13: 5726 | C13: 12.08 | D13: =VLOOKUP(B13,'Plan Comptable'!A:B,2,FALSE) -> Trés. / comptabilité
A14: 45680 | B14: 1010 | C14: -1450 | D14: =VLOOKUP(B14,'Plan Comptable'!A:B,2,FALSE) -> 0033830-EOP Épargne avec opérations (C) | E14: Roger St-Michel
A15: 45680 | B15: 5725 | C15: 1450 | D15: =VLOOKUP(B15,'Plan Comptable'!A:B,2,FALSE) -> Dépenses de gestion | E15: Roger St-Michel
A16: 45680 | B16: 1010 | C16: -1006.03 | D16: =VLOOKUP(B16,'Plan Comptable'!A:B,2,FALSE) -> 0033830-EOP Épargne avec opérations (C)
A17: 45680 | B17: 5700 | C17: 1006.03 | D17: =VLOOKUP(B17,'Plan Comptable'!A:B,2,FALSE) -> Déneigement + à la main
A18: 45688 | B18: 1010 | C18: -5.95 | D18: =VLOOKUP(B18,'Plan Comptable'!A:B,2,FALSE) -> 0033830-EOP Épargne avec opérations (C)
A19: 45688 | B19: 5720 | C19: 5.95 | D19: =VLOOKUP(B19,'Plan Comptable'!A:B,2,FALSE) -> Frais de banque
A20: 45688 | B20: 1010 | C20: -5 | D20: =VLOOKUP(B20,'Plan Comptable'!A:B,2,FALSE) -> 0033830-EOP Épargne avec opérations (C)
A21: 45688 | B21: 5720 | C21: 5 | D21: =VLOOKUP(B21,'Plan Comptable'!A:B,2,FALSE) -> Frais de banque
A22: 45688 | B22: 4290 | C22: 0.01 | D22: =VLOOKUP(B22,'Plan Comptable'!A:B,2,FALSE) -> Produits d'intérêts
A23: 45688 | B23: 1100 | C23: 0.01 | D23: =VLOOKUP(B23,'Plan Comptable'!A:B,2,FALSE) -> 0033830-ET1 Compte avantage entreprise
A24: 45688 | B24: 4290 | C24: 201.71 | D24: =VLOOKUP(B24,'Plan Comptable'!A:B,2,FALSE) -> Produits d'intérêts
A25: 45688 | B25: 1105 | C25: 201.71 | D25: =VLOOKUP(B25,'Plan Comptable'!A:B,2,FALSE) -> 0033830-ET2 Compte avantage entreprise
A26: 45691 | B26: 4160 | C26: 212 | D26: =VLOOKUP(B26,'Plan Comptable'!A:B,2,FALSE) -> Cotisation
A27: 45691 | B27: 1010 | C27: 212 | D27: =VLOOKUP(B27,'Plan Comptable'!A:B,2,FALSE) -> 0033830-EOP Épargne avec opérations (C)
... A57: 45748 | B57: 1010 | C57: 2332.73 | D57: =VLOOKUP(B57,'Plan Comptable'!A:B,2,FALSE) -> 0033830-EOP Épargne avec opérations (C)
A58: 45749 | B58: 1010 | C58: -280 | D58: =VLOOKUP(B58,'Plan Comptable'!A:B,2,FALSE) -> 0033830-EOP Épargne avec opérations (C) | E58: Roger St-Michel
A59: 45749 | B59: 5725 | C59: 280 | D59: =VLOOKUP(B59,'Plan Comptable'!A:B,2,FALSE) -> Dépenses de gestion | E59: Roger St-Michel
A60: 45749 | B60: 1010 | C60: -420 | D60: =VLOOKUP(B60,'Plan Comptable'!A:B,2,FALSE) -> 0033830-EOP Épargne avec opérations (C) | E60: Thalia Beaudry
A61: 45749 | B61: 5725 | C61: 420 | D61: =VLOOKUP(B61,'Plan Comptable'!A:B,2,FALSE) -> Dépenses de gestion | E61: Thalia Beaudry
A62: 45754 | B62: 1010 | C62: -360 | D62: =VLOOKUP(B62,'Plan Comptable'!A:B,2,FALSE) -> 0033830-EOP Épargne avec opérations (C) | E62: Jean-Maurice Breton
A63: 45754 | B63: 5725 | C63: 360 | D63: =VLOOKUP(B63,'Plan Comptable'!A:B,2,FALSE) -> Dépenses de gestion | E63: Jean-Maurice Breton
A64: 45758 | B64: 1010 | C64: -63.26 | D64: =VLOOKUP(B64,'Plan Comptable'!A:B,2,FALSE) -> 0033830-EOP Épargne avec opérations (C) | E64: Hydro-québec
A65: 45758 | B65: 5680 | C65: 63.26 | D65: =VLOOKUP(B65,'Plan Comptable'!A:B,2,FALSE) -> Entretien & rép. ext. | E65: Hydro-québec
A66: 45761 | B66: 1010 | C66: -12.08 | D66: =VLOOKUP(B66,'Plan Comptable'!A:B,2,FALSE) -> 0033830-EOP Épargne avec opérations (C)
A67: 45761 | B67: 5726 | C67: 12.08 | D67: =VLOOKUP(B67,'Plan Comptable'!A:B,2,FALSE) -> Trés. / comptabilité
A68: 45775 | B68: 1010 | C68: -1014.08 | D68: =VLOOKUP(B68,'Plan Comptable'!A:B,2,FALSE) -> 0033830-EOP Épargne avec opérations (C) | E68: Tondeuse
A69: 45775 | B69: 5680 | C69: 1014.08 | D69: =VLOOKUP(B69,'Plan Comptable'!A:B,2,FALSE) -> Entretien & rép. ext. | E69: Tondeuse
A70: 45777 | B70: 1010 | C70: -5.95 | D70: =VLOOKUP(B70,'Plan Comptable'!A:B,2,FALSE) -> 0033830-EOP Épargne avec opérations (C)
A71: 45777 | B71: 5720 | C71: 5.95 | D71: =VLOOKUP(B71,'Plan Comptable'!A:B,2,FALSE) -> Frais de banque
A72: 45777 | B72: 1010 | C72: -7.7 | D72: =VLOOKUP(B72,'Plan Comptable'!A:B,2,FALSE) -> 0033830-EOP Épargne avec opérations (C)
A73: 45777 | B73: 5720 | C73: 7.7 | D73: =VLOOKUP(B73,'Plan Comptable'!A:B,2,FALSE) -> Frais de banque
A74: 45777 | B74: 4290 | C74: 0.01 | D74: =VLOOKUP(B74,'Plan Comptable'!A:B,2,FALSE) -> Produits d'intérêts
A75: 45777 | B75: 1100 | C75: 0.01 | D75: =VLOOKUP(B75,'Plan Comptable'!A:B,2,FALSE) -> 0033830-ET1 Compte avantage entreprise
A76: 45777 | B76: 4290 | C76: 165.79 | D76: =VLOOKUP(B76,'Plan Comptable'!A:B,2,FALSE) -> Produits d'intérêts
A77: 45777 | B77: 1105 | C77: 165.79 | D77: =VLOOKUP(B77,'Plan Comptable'!A:B,2,FALSE) -> 0033830-ET2 Compte avantage entreprise
A78: 45778 | B78: 4160 | C78: 2332.73 | D78: =VLOOKUP(B78,'Plan Comptable'!A:B,2,FALSE) -> Cotisation
A79: 45778 | B79: 1010 | C79: 2332.73 | D79: =VLOOKUP(B79,'Plan Comptable'!A:B,2,FALSE) -> 0033830-EOP Épargne avec opérations (C)
A80: 45779 | B80: 4160 | C80: 212 | D80: =VLOOKUP(B80,'Plan Comptable'!A:B,2,FALSE) -> Cotisation
A81: 45779 | B81: 1010 | C81: 212 | D81: =VLOOKUP(B81,'Plan Comptable'!A:B,2,FALSE) -> 0033830-EOP Épargne avec opérations (C)
... A83: 45782 | B83: 5650 | C83: 1368.22 | D83: =VLOOKUP(B83,'Plan Comptable'!A:B,2,FALSE) -> Assurances
A84: 45785 | B84: 1010 | C84: -1391.19 | D84: =VLOOKUP(B84,'Plan Comptable'!A:B,2,FALSE) -> 0033830-EOP Épargne avec opérations (C) | E84: Tondeuse
A85: 45785 | B85: 5680 | C85: 1391.19 | D85: =VLOOKUP(B85,'Plan Comptable'!A:B,2,FALSE) -> Entretien & rép. ext. | E85: Tondeuse
A86: 45790 | B86: 1010 | C86: -12.08 | D86: =VLOOKUP(B86,'Plan Comptable'!A:B,2,FALSE) -> 0033830-EOP Épargne avec opérations (C)
A87: 45790 | B87: 5726 | C87: 12.08 | D87: =VLOOKUP(B87,'Plan Comptable'!A:B,2,FALSE) -> Trés. / comptabilité
A88: 45798 | B88: 1010 | C88: -171.52 | D88: =VLOOKUP(B88,'Plan Comptable'!A:B,2,FALSE) -> 0033830-EOP Épargne avec opérations (C) | E88: Paiement de sinistre, Voir soumission
A89: 45798 | B89: 5690 | C89: 171.52 | D89: =VLOOKUP(B89,'Plan Comptable'!A:B,2,FALSE) -> Entretien & rép. bâtiment | E89: Paiement de sinistre, Voir soumission
A90: 45803 | B90: 1010 | C90: -400.11 | D90: =VLOOKUP(B90,'Plan Comptable'!A:B,2,FALSE) -> 0033830-EOP Épargne avec opérations (C) | E90: Facture à payer de Plombdrain, le plombier qui est venu réparer la plomberie défectueuse, en urgence, chez Mme Gilbert.
A91: 45803 | B91: 5690 | C91: 400.11 | D91: =VLOOKUP(B91,'Plan Comptable'!A:B,2,FALSE) -> Entretien & rép. bâtiment | E91: Facture à payer de Plombdrain, le plombier qui est venu réparer la plomberie défectueuse, en urgence, chez Mme Gilbert.
A92: 45806 | B92: 4160 | C92: 212 | D92: =VLOOKUP(B92,'Plan Comptable'!A:B,2,FALSE) -> Cotisation
A93: 45806 | B93: 1010 | C93: 212 | D93: =VLOOKUP(B93,'Plan Comptable'!A:B,2,FALSE) -> 0033830-EOP Épargne avec opérations (C)
A94: 45807 | B94: 1010 | C94: -5.95 | D94: =VLOOKUP(B94,'Plan Comptable'!A:B,2,FALSE) -> 0033830-EOP Épargne avec opérations (C)
A95: 45807 | B95: 5720 | C95: 5.95 | D95: =VLOOKUP(B95,'Plan Comptable'!A:B,2,FALSE) -> Frais de banque
A96: 45807 | B96: 1010 | C96: -5 | D96: =VLOOKUP(B96,'Plan Comptable'!A:B,2,FALSE) -> 0033830-EOP Épargne avec opérations (C)
A97: 45807 | B97: 5720 | C97: 5 | D97: =VLOOKUP(B97,'Plan Comptable'!A:B,2,FALSE) -> Frais de banque
A98: 45807 | B98: 4290 | C98: 0.01 | D98: =VLOOKUP(B98,'Plan Comptable'!A:B,2,FALSE) -> Produits d'intérêts
A99: 45807 | B99: 1100 | C99: 0.01 | D99: =VLOOKUP(B99,'Plan Comptable'!A:B,2,FALSE) -> 0033830-ET1 Compte avantage entreprise
A100: 45807 | B100: 4290 | C100: 171.62 | D100: =VLOOKUP(B100,'Plan Comptable'!A:B,2,FALSE) -> Produits d'intérêts
A101: 45807 | B101: 1105 | C101: 171.62 | D101: =VLOOKUP(B101,'Plan Comptable'!A:B,2,FALSE) -> 0033830-ET2 Compte avantage entreprise
A102: 45810 | B102: 4160 | C102: 2332.73 | D102: =VLOOKUP(B102,'Plan Comptable'!A:B,2,FALSE) -> Cotisation
A103: 45810 | B103: 1010 | C103: 2332.73 | D103: =VLOOKUP(B103,'Plan Comptable'!A:B,2,FALSE) -> 0033830-EOP Épargne avec opérations (C)
... A109: 45821 | B109: 5726 | C109: 12.08 | D109: =VLOOKUP(B109,'Plan Comptable'!A:B,2,FALSE) -> Trés. / comptabilité
A110: 45824 | B110: 1010 | C110: -755.39 | D110: =VLOOKUP(B110,'Plan Comptable'!A:B,2,FALSE) -> 0033830-EOP Épargne avec opérations (C) | E110: Traitement Araigné, Voir facture
A111: 45824 | B111: 5690 | C111: 755.39 | D111: =VLOOKUP(B111,'Plan Comptable'!A:B,2,FALSE) -> Entretien & rép. bâtiment | E111: Traitement Araigné, Voir facture
A112: 45825 | B112: 1010 | C112: -143.72 | D112: =VLOOKUP(B112,'Plan Comptable'!A:B,2,FALSE) -> 0033830-EOP Épargne avec opérations (C) | E112: Traitement Fourmi, Voir facture
A113: 45825 | B113: 5690 | C113: 143.72 | D113: =VLOOKUP(B113,'Plan Comptable'!A:B,2,FALSE) -> Entretien & rép. bâtiment | E113: Traitement Fourmi, Voir facture
A114: 45828 | B114: 5725 | C114: 314.09 | D114: =VLOOKUP(B114,'Plan Comptable'!A:B,2,FALSE) -> Dépenses de gestion | E114: Conférence Legault Dubois, Voir facture
A115: 45828 | B115: 1010 | C115: -314.09 | D115: =VLOOKUP(B115,'Plan Comptable'!A:B,2,FALSE) -> 0033830-EOP Épargne avec opérations (C) | E115: Conférence Legault Dubois, Voir facture
A116: 45834 | B116: 5680 | C116: 366.66 | D116: =VLOOKUP(B116,'Plan Comptable'!A:B,2,FALSE) -> Entretien & rép. ext. | E116: Alarme Supérieure, Voir facture
A117: 45834 | B117: 1010 | C117: -366.66 | D117: =VLOOKUP(B117,'Plan Comptable'!A:B,2,FALSE) -> 0033830-EOP Épargne avec opérations (C) | E117: Alarme Supérieure, Voir facture
A118: 45838 | B118: 4160 | C118: 212 | D118: =VLOOKUP(B118,'Plan Comptable'!A:B,2,FALSE) -> Cotisation
A119: 45838 | B119: 1010 | C119: 212 | D119: =VLOOKUP(B119,'Plan Comptable'!A:B,2,FALSE) -> 0033830-EOP Épargne avec opérations (C)
A120: 45838 | B120: 1010 | C120: -5.95 | D120: =VLOOKUP(B120,'Plan Comptable'!A:B,2,FALSE) -> 0033830-EOP Épargne avec opérations (C)
A121: 45838 | B121: 5720 | C121: 5.95 | D121: =VLOOKUP(B121,'Plan Comptable'!A:B,2,FALSE) -> Frais de banque
A122: 45838 | B122: 1010 | C122: -7.7 | D122: =VLOOKUP(B122,'Plan Comptable'!A:B,2,FALSE) -> 0033830-EOP Épargne avec opérations (C)
A123: 45838 | B123: 5720 | C123: 7.7 | D123: =VLOOKUP(B123,'Plan Comptable'!A:B,2,FALSE) -> Frais de banque
A124: 45838 | B124: 4290 | C124: 0.01 | D124: =VLOOKUP(B124,'Plan Comptable'!A:B,2,FALSE) -> Produits d'intérêts
A125: 45838 | B125: 1100 | C125: 0.01 | D125: =VLOOKUP(B125,'Plan Comptable'!A:B,2,FALSE) -> 0033830-ET1 Compte avantage entreprise
A126: 45838 | B126: 4290 | C126: 166.38 | D126: =VLOOKUP(B126,'Plan Comptable'!A:B,2,FALSE) -> Produits d'intérêts
A127: 45838 | B127: 1105 | C127: 166.38 | D127: =VLOOKUP(B127,'Plan Comptable'!A:B,2,FALSE) -> 0033830-ET2 Compte avantage entreprise
A128: 45839 | B128: 4160 | C128: 636.11 | D128: =VLOOKUP(B128,'Plan Comptable'!A:B,2,FALSE) -> Cotisation
A129: 45839 | B129: 1010 | C129: 636.11 | D129: =VLOOKUP(B129,'Plan Comptable'!A:B,2,FALSE) -> 0033830-EOP Épargne avec opérations (C)
... A135: 45852 | B135: 5726 | C135: 12.08 | D135: =VLOOKUP(B135,'Plan Comptable'!A:B,2,FALSE) -> Trés. / comptabilité
A136: 45867 | B136: 1010 | C136: -340 | D136: =VLOOKUP(B136,'Plan Comptable'!A:B,2,FALSE) -> 0033830-EOP Épargne avec opérations (C) | E136: Thalia Beaudry
A137: 45867 | B137: 5725 | C137: 340 | D137: =VLOOKUP(B137,'Plan Comptable'!A:B,2,FALSE) -> Dépenses de gestion | E137: Thalia Beaudry
A138: 45867 | B138: 1010 | C138: -320 | D138: =VLOOKUP(B138,'Plan Comptable'!A:B,2,FALSE) -> 0033830-EOP Épargne avec opérations (C) | E138: Jean-Maurice Breton
A139: 45867 | B139: 5725 | C139: 320 | D139: =VLOOKUP(B139,'Plan Comptable'!A:B,2,FALSE) -> Dépenses de gestion | E139: Jean-Maurice Breton
A140: 45867 | B140: 1010 | C140: -340 | D140: =VLOOKUP(B140,'Plan Comptable'!A:B,2,FALSE) -> 0033830-EOP Épargne avec opérations (C) | E140: Roger St-Michel
...

Sheet Plan Comptable
A1: NO | B1: COMPTE
A2: 1010 | B2: 0033830-EOP Épargne avec opérations (C)
A3: 1050 | B3: 0033830-ES1 Épargne stable à intérêt quotidien
A4: 1100 | B4: 0033830-ET1 Compte avantage entreprise
A5: 1105 | B5: 0033830-ET2 Compte avantage entreprise
A6: 1110 | B6: Intérêts à recevoir
A7: 4160 | B7: Cotisation
A8: 4290 | B8: Produits d'intérêts
A9: 5650 | B9: Assurances
A10: 5660 | B10: Électricité
A11: 5670 | B11: Entretien ménager
A12: 5680 | B12: Entretien & rép. ext.
A13: 5690 | B13: Entretien & rép. bâtiment
... A23: 3200 | B23: Apport
